dualPredictor/__init__.py
dualPredictor/df_preprocess.py
dualPredictor/dual_model.py
dualPredictor/model_plot.py
dualPredictor-0.0.31.dist-info/LICENSE
dualPredictor-0.0.31.dist-info/METADATA
dualPredictor-0.0.31.dist-info/WHEEL
dualPredictor-0.0.31.dist-info/top_level.txt
dualPredictor-0.0.31.dist-info/RECORD
